moveread/pipelines/extract_validation/__init__.py
moveread/pipelines/extract_validation/__init__.pyi
moveread/pipelines/extract_validation/main.py
moveread/pipelines/extract_validation/types.py
moveread_pipelines_extract_validation-0.1.8.dist-info/METADATA
moveread_pipelines_extract_validation-0.1.8.dist-info/WHEEL
moveread_pipelines_extract_validation-0.1.8.dist-info/top_level.txt
moveread_pipelines_extract_validation-0.1.8.dist-info/RECORD
