Metadata-Version: 2.1
Name: moveread-pipelines-extract-validation
Version: 0.1.8
Summary: Pipeline interface for the auto-extract validation API
Author-email: Marcel Claramunt <marcel@moveread.com>
Project-URL: repo, https://github.com/moveread/moveread-pipelines.git
Requires-Python: >=3.10
Requires-Dist: queue-api
Requires-Dist: pydantic ==2.*
Requires-Dist: lazy-loader
Requires-Dist: pipeteer
